[
	{
	"name_A" : "dancer_frame_30_after_before.mp4",
	"IfImage" : "false"
	},
	{
	"name_A" : "soldier_frame_20_after_before.mp4",
	"IfImage" : "false"
	},
	{
	"name_A" : "skull_40_after_before.mp4",
	"IfImage" : "false"
	},
	{
	"name_A" : "basketball_40_before_after.mp4",
	"IfImage" : "false"
	},
	{
	"name_A" : "exercise_frame_20_after_before.mp4",
	"IfImage" : "false"
	},
	{
	"name_A" : "dancer_40_before_after.mp4",
	"IfImage" : "false"
	},
	{
	"name_A" : "redandblack_frame_20_before_after.mp4",
	"IfImage" : "false"
	},
	{
	"name_A" : "Earth-2_20_after_before.mp4",
	"IfImage" : "false"
	},
	{
	"name_A" : "redandblack_30_after_before.mp4",
	"IfImage" : "false"
	},
	{
	"name_A" : "Earth-2_40_before_after.mp4",
	"IfImage" : "false"
	},
	{
	"name_A" : "can_30_before_after.mp4",
	"IfImage" : "false"
	},
	{
	"name_A" : "exercise_40_after_before.mp4",
	"IfImage" : "false"
	},
	{
	"name_A" : "skull_30_after_before.mp4",
	"IfImage" : "false"
	},
	{
	"name_A" : "dancer_20_before_after.mp4",
	"IfImage" : "false"
	},
	{
	"name_A" : "earth_30_before_after.mp4",
	"IfImage" : "false"
	},
	{
	"name_A" : "redandblack_frame_30_before_after.mp4",
	"IfImage" : "false"
	},
	{
	"name_A" : "basketball_frame_30_before_after.mp4",
	"IfImage" : "false"
	},
	{
	"name_A" : "soldier_frame_40_after_before.mp4",
	"IfImage" : "false"
	},
	{
	"name_A" : "exercise_30_after_before.mp4",
	"IfImage" : "false"
	},
	{
	"name_A" : "redandblack_20_before_after.mp4",
	"IfImage" : "false"
	},
	{
	"name_A" : "skull_20_after_before.mp4",
	"IfImage" : "false"
	},
	{
	"name_A" : "soldier_frame_30_before_after.mp4",
	"IfImage" : "false"
	},
	{
	"name_A" : "dancer_frame_40_after_before.mp4",
	"IfImage" : "false"
	},
	{
	"name_A" : "redandblack_40_before_after.mp4",
	"IfImage" : "false"
	},
	{
	"name_A" : "basketball_20_after_before.mp4",
	"IfImage" : "false"
	},
	{
	"name_A" : "dancer_frame_20_after_before.mp4",
	"IfImage" : "false"
	},
	{
	"name_A" : "exercise_20_before_after.mp4",
	"IfImage" : "false"
	},
	{
	"name_A" : "dancer_20_after_before.mp4",
	"IfImage" : "false"
	},
	{
	"name_A" : "exercise_frame_40_after_before.mp4",
	"IfImage" : "false"
	},
	{
	"name_A" : "basketball_30_after_before.mp4",
	"IfImage" : "false"
	},
	{
	"name_A" : "exercise_frame_20_before_before.mp4",
	"IfImage" : "false"
	},
	{
	"name_A" : "dancer_30_after_before.mp4",
	"IfImage" : "false"
	},
	{
	"name_A" : "Earth-2_40_after_before.mp4",
	"IfImage" : "false"
	},
	{
	"name_A" : "basketball_30_before_after.mp4",
	"IfImage" : "false"
	},
	{
	"name_A" : "Earth-2_30_before_after.mp4",
	"IfImage" : "false"
	},
	{
	"name_A" : "basketball_frame_40_after_before.mp4",
	"IfImage" : "false"
	},
	{
	"name_A" : "redandblack_20_after_before.mp4",
	"IfImage" : "false"
	},
	{
	"name_A" : "can_40_before_after.mp4",
	"IfImage" : "false"
	},
	{
	"name_A" : "soldier_20_before_after.mp4",
	"IfImage" : "false"
	},
	{
	"name_A" : "earth_20_after_before.mp4",
	"IfImage" : "false"
	},
	{
	"name_A" : "soldier_30_before_after.mp4",
	"IfImage" : "false"
	},
	{
	"name_A" : "basketball_frame_40_before_after.mp4",
	"IfImage" : "false"
	},
	{
	"name_A" : "earth_30_after_before.mp4",
	"IfImage" : "false"
	},
	{
	"name_A" : "can_20_after_before.mp4",
	"IfImage" : "false"
	},
	{
	"name_A" : "earth_40_after_before.mp4",
	"IfImage" : "false"
	},
	{
	"name_A" : "redandblack_frame_40_before_after.mp4",
	"IfImage" : "false"
	},
	{
	"name_A" : "basketball_40_after_after.mp4",
	"IfImage" : "false"
	},
	{
	"name_A" : "exercise_frame_30_before_after.mp4",
	"IfImage" : "false"
	},
	{
	"name_A" : "basketball_frame_20_after_before.mp4",
	"IfImage" : "false"
	},
	{
	"name_A" : "soldier_40_after_before.mp4",
	"IfImage" : "false"
	}
]
